Workbook
Name Slicer_Country_ShortForm: #N/A
Name Slicer_Year: #N/A

Sheet Main
A1: Year | B1: Month | C1: Hotel Name | D1: Country | E1: City | F1: Customer ID | G1: Customer Age | H1: Customer Gender | I1: Customer Type | J1: Booking Date | K1: Room Type | L1: Booking Status | M1: Room Booked | N1: Room Available | O1: Price | P1: Payment Mode | Q1: Total Revenue | R1: Profit | S1: Country ShortForm
A2: 2022 | B2: Jan | C2: Opera House | D2: Australia | E2: Sydney | F2: CID00 | G2: 37 | H2: Female | I2: Existing | J2: 44570 | K2: Business Class | L2: Cancelled | M2: 9 | N2: 123 | O2: 4867 | P2: Online | Q2: =Table2[[#This Row],[Room Booked]]*Table2[[#This Row],[Price]] -> 43803 | R2: 32122.2 | S2: {=_xlfn.XLOOKUP(Table2[[#This Row],[Country]],_xlfn.ANCHORARRAY($W$2),$X$2:$X$7)} -> AUS | W2: {=_xlfn.UNIQUE(Table2[Country])} -> Australia | X2: AUS
A3: 2022 | B3: Apr | C3: Hames Palace | D3: United Kingdom | E3: London | F3: CID01 | G3: 21 | H3: Male | I3: Existing | J3: 44674 | K3: Business Class | L3: Pending | M3: 26 | N3: 106 | O3: 3928 | P3: Credit Card | Q3: =Table2[[#This Row],[Room Booked]]*Table2[[#This Row],[Price]] -> 102128 | R3: 44779.2 | S3: {=_xlfn.XLOOKUP(Table2[[#This Row],[Country]],_xlfn.ANCHORARRAY($W$2),$X$2:$X$7)} -> UK | W3: United Kingdom | X3: UK
A4: 2022 | B4: Jun | C4: Marine Resort | D4: India | E4: Mumbai | F4: CID03 | G4: 22 | H4: Female | I4: New | J4: 44721 | K4: Single | L4: Confirmed | M4: 11 | N4: 123 | O4: 26016 | P4: Online | Q4: =Table2[[#This Row],[Room Booked]]*Table2[[#This Row],[Price]] -> 286176 | R4: 26341.2 | S4: {=_xlfn.XLOOKUP(Table2[[#This Row],[Country]],_xlfn.ANCHORARRAY($W$2),$X$2:$X$7)} -> IND | W4: India | X4: IND
A5: 2022 | B5: Oct | C5: Opera House | D5: Australia | E5: Sydney | F5: CID08 | G5: 56 | H5: Female | I5: New | J5: 44837 | K5: Super Luxury | L5: Pending | M5: 19 | N5: 86 | O5: 4639 | P5: Online | Q5: =Table2[[#This Row],[Room Booked]]*Table2[[#This Row],[Price]] -> 88141 | R5: 65409.9 | S5: {=_xlfn.XLOOKUP(Table2[[#This Row],[Country]],_xlfn.ANCHORARRAY($W$2),$X$2:$X$7)} -> AUS | W5: United States | X5: USA
A6: 2022 | B6: Dec | C6: Hames Palace | D6: United Kingdom | E6: London | F6: CID09 | G6: 56 | H6: Female | I6: Existing | J6: 44914 | K6: Sharing | L6: Pending | M6: 47 | N6: 121 | O6: 73568 | P6: Cash | Q6: =Table2[[#This Row],[Room Booked]]*Table2[[#This Row],[Price]] -> 3457696 | R6: 197433.6 | S6: {=_xlfn.XLOOKUP(Table2[[#This Row],[Country]],_xlfn.ANCHORARRAY($W$2),$X$2:$X$7)} -> UK | W6: United Arab Emirates | X6: UAE
A7: 2023 | B7: Sep | C7: Marine Resort | D7: India | E7: Mumbai | F7: CID12 | G7: 52 | H7: Male | I7: Existing | J7: 45184 | K7: Business Class | L7: Cancelled | M7: 22 | N7: 123 | O7: 7380 | P7: Online | Q7: =Table2[[#This Row],[Room Booked]]*Table2[[#This Row],[Price]] -> 162360 | R7: 121770 | S7: {=_xlfn.XLOOKUP(Table2[[#This Row],[Country]],_xlfn.ANCHORARRAY($W$2),$X$2:$X$7)} -> IND | W7: Italy | X7: ITA
A8: 2022 | B8: Mar | C8: Opera House | D8: Australia | E8: Sydney | F8: CID14 | G8: 64 | H8: Female | I8: Existing | J8: 44646 | K8: Business Class | L8: Pending | M8: 26 | N8: 114 | O8: 3976 | P8: Cash | Q8: =Table2[[#This Row],[Room Booked]]*Table2[[#This Row],[Price]] -> 103376 | R8: 75146.4 | S8: {=_xlfn.XLOOKUP(Table2[[#This Row],[Country]],_xlfn.ANCHORARRAY($W$2),$X$2:$X$7)} -> AUS
A9: 2022 | B9: Aug | C9: Hames Palace | D9: United Kingdom | E9: London | F9: CID15 | G9: 22 | H9: Male | I9: Existing | J9: 44782 | K9: Single | L9: Cancelled | M9: 38 | N9: 105 | O9: 35248 | P9: Credit Card | Q9: =Table2[[#This Row],[Room Booked]]*Table2[[#This Row],[Price]] -> 1339424 | R9: 91204.2 | S9: {=_xlfn.XLOOKUP(Table2[[#This Row],[Country]],_xlfn.ANCHORARRAY($W$2),$X$2:$X$7)} -> UK
A10: 2023 | B10: May | C10: Marine Resort | D10: India | E10: Mumbai | F10: CID16 | G10: 49 | H10: Female | I10: Existing | J10: 45062 | K10: Single | L10: Cancelled | M10: 62 | N10: 109 | O10: 42008 | P10: Credit Card | Q10: =Table2[[#This Row],[Room Booked]]*Table2[[#This Row],[Price]] -> 2604496 | R10: 97668.6 | S10: {=_xlfn.XLOOKUP(Table2[[#This Row],[Country]],_xlfn.ANCHORARRAY($W$2),$X$2:$X$7)} -> IND
A11: 2022 | B11: Jan | C11: Empire Grand | D11: United States | E11: New York | F11: CID17 | G11: 46 | H11: Female | I11: New | J11: 44576 | K11: Sharing | L11: Pending | M11: 16 | N11: 99 | O11: 20104 | P11: Debit Card | Q11: =Table2[[#This Row],[Room Booked]]*Table2[[#This Row],[Price]] -> 321664 | R11: 104549.4 | S11: {=_xlfn.XLOOKUP(Table2[[#This Row],[Country]],_xlfn.ANCHORARRAY($W$2),$X$2:$X$7)} -> USA
A12: 2022 | B12: Oct | C12: Opera House | D12: Australia | E12: Sydney | F12: CID23 | G12: 38 | H12: Female | I12: Existing | J12: 44850 | K12: Regular | L12: Pending | M12: 16 | N12: 115 | O12: 9707 | P12: Debit Card | Q12: =Table2[[#This Row],[Room Booked]]*Table2[[#This Row],[Price]] -> 155312 | R12: 270825.3 | S12: {=_xlfn.XLOOKUP(Table2[[#This Row],[Country]],_xlfn.ANCHORARRAY($W$2),$X$2:$X$7)} -> AUS
A13: 2023 | B13: Sep | C13: Opera House | D13: Australia | E13: Sydney | F13: CID24 | G13: 56 | H13: Female | I13: Existing | J13: 45182 | K13: Business Class | L13: Pending | M13: 24 | N13: 80 | O13: 340 | P13: Online | Q13: =Table2[[#This Row],[Room Booked]]*Table2[[#This Row],[Price]] -> 8160 | R13: 6018 | S13: {=_xlfn.XLOOKUP(Table2[[#This Row],[Country]],_xlfn.ANCHORARRAY($W$2),$X$2:$X$7)} -> AUS
A14: 2023 | B14: Jun | C14: Hames Palace | D14: United Kingdom | E14: London | F14: CID26 | G14: 35 | H14: Male | I14: New | J14: 45095 | K14: Delux | L14: Cancelled | M14: 27 | N14: 109 | O14: 76704 | P14: Cash | Q14: =Table2[[#This Row],[Room Booked]]*Table2[[#This Row],[Price]] -> 2071008 | R14: 86702.7 | S14: {=_xlfn.XLOOKUP(Table2[[#This Row],[Country]],_xlfn.ANCHORARRAY($W$2),$X$2:$X$7)} -> UK
A15: 2022 | B15: Nov | C15: Palace Inn | D15: United Arab Emirates | E15: Abu Dhabi | F15: CID27 | G15: 56 | H15: Female | I15: New | J15: 44892 | K15: Sharing | L15: Confirmed | M15: 34 | N15: 96 | O15: 17304 | P15: Online | Q15: =Table2[[#This Row],[Room Booked]]*Table2[[#This Row],[Price]] -> 588336 | R15: 17952.9 | S15: {=_xlfn.XLOOKUP(Table2[[#This Row],[Country]],_xlfn.ANCHORARRAY($W$2),$X$2:$X$7)} -> UAE
A16: 2023 | B16: Oct | C16: Opera House | D16: Australia | E16: Sydney | F16: CID33 | G16: 56 | H16: Female | I16: Existing | J16: 45202 | K16: Sharing | L16: Cancelled | M16: 14 | N16: 105 | O16: 155856 | P16: Online | Q16: =Table2[[#This Row],[Room Booked]]*Table2[[#This Row],[Price]] -> 2181984 | R16: 64290.6 | S16: {=_xlfn.XLOOKUP(Table2[[#This Row],[Country]],_xlfn.ANCHORARRAY($W$2),$X$2:$X$7)} -> AUS
A17: 2022 | B17: Oct | C17: Opera House | D17: Australia | E17: Sydney | F17: CID36 | G17: 55 | H17: Female | I17: Existing | J17: 44860 | K17: Regular | L17: Pending | M17: 21 | N17: 92 | O17: 1945 | P17: Cash | Q17: =Table2[[#This Row],[Room Booked]]*Table2[[#This Row],[Price]] -> 40845 | R17: 19255.5 | S17: {=_xlfn.XLOOKUP(Table2[[#This Row],[Country]],_xlfn.ANCHORARRAY($W$2),$X$2:$X$7)} -> AUS
A18: 2023 | B18: Jul | C18: Palace Inn | D18: United Arab Emirates | E18: Abu Dhabi | F18: CID38 | G18: 19 | H18: Female | I18: Existing | J18: 45138 | K18: Single | L18: Confirmed | M18: 16 | N18: 110 | O18: 75528 | P18: Debit Card | Q18: =Table2[[#This Row],[Room Booked]]*Table2[[#This Row],[Price]] -> 1208448 | R18: 107627.4 | S18: {=_xlfn.XLOOKUP(Table2[[#This Row],[Country]],_xlfn.ANCHORARRAY($W$2),$X$2:$X$7)} -> UAE
A19: 2022 | B19: Sep | C19: Empire Grand | D19: United States | E19: New York | F19: CID39 | G19: 58 | H19: Female | I19: Existing | J19: 44811 | K19: Regular | L19: Pending | M19: 16 | N19: 119 | O19: 1683 | P19: Debit Card | Q19: =Table2[[#This Row],[Room Booked]]*Table2[[#This Row],[Price]] -> 26928 | R19: 19691.1 | S19: {=_xlfn.XLOOKUP(Table2[[#This Row],[Country]],_xlfn.ANCHORARRAY($W$2),$X$2:$X$7)} -> USA
... A141: 2022 | B141: Feb | C141: Empire Grand | D141: United States | E141: Chicago | F141: CID08 | G141: 46 | H141: Female | I141: Existing | J141: 44607 | K141: Sharing | L141: Pending | M141: 16 | N141: 99 | O141: 220104 | P141: Debit Card | Q141: =Table2[[#This Row],[Room Booked]]*Table2[[#This Row],[Price]] -> 3521664 | R141: 104549.4 | S141: {=_xlfn.XLOOKUP(Table2[[#This Row],[Country]],_xlfn.ANCHORARRAY($W$2),$X$2:$X$7)} -> USA

Sheet Pivot
A1: Total | E1: Hotel Room | O1: Month | T1: City | X1: Country | AB1: ID | AF1: Type | AK1: Room Type
A4: Total Tranasction | B4: Total Hotel Room | E4: Hotel Room Available | H4: Hotel Room Available | K4: Hotel Room Booked | O4: Revenue & Profit by Month | T4: Room Available by City | X4: Room Booked In Country | AB4: Room Available by City | AF4: Customer Type | AK4: Room Available & Room Booked by Room Type
A5: 140 | B5: =_xlfn.LET(_xlpm.x,_xlfn.UNIQUE(Table2[[Hotel Name]:[City]]),COUNTA(_xlfn.CHOOSECOLS(_xlpm.x,1))) -> 33
E6: Row Labels | F6: Count of Hotel Name | H6: Row Labels | I6: Sum of Room Available | K6: Row Labels | L6: Sum of Room Booked | O6: Row Labels | P6: Sum of Total Revenue | Q6: Sum of Profit | T6: Row Labels | U6: Sum of Room Available | X6: Row Labels | Y6: Sum of Room Booked | AB6: Row Labels | AC6: Sum of Room Available | AF6: Row Labels | AG6: Count of Customer ID | AH6: Count of Customer ID2 | AK6: Row Labels | AL6: Sum of Room Booked | AM6: Sum of Room Available
A7: Total County | B7: Total City | E7: Empire Grand | F7: 20 | H7: Empire Grand | I7: 2093 | K7: Marine Resort | L7: 1004 | O7: Jan | P7: 33529395 | Q7: 1108296.3 | T7: Abu Dhabi | U7: 1902 | X7: AUS | Y7: 753 | AB7: CID00 | AC7: 629 | AF7: Existing | AG7: 95 | AH7: 0.67857143 | AK7: Sharing | AL7: 850 | AM7: 3523
A8: =COUNTA(_xlfn.UNIQUE(Table2[Country])) -> 6 | B8: =COUNTA(_xlfn.UNIQUE(Table2[City])) -> 12 | E8: Hames Palace | F8: 19 | H8: Hames Palace | I8: 2120 | K8: Hames Palace | L8: 622 | O8: Feb | P8: 34322928 | Q8: 953682 | T8: Bangalore | U8: 1112 | X8: IND | Y8: 889 | AB8: CID01 | AC8: 524 | AF8: New | AG8: 45 | AH8: 0.32142857 | AK8: Delux | AL8: 456 | AM8: 2163
E9: Hotel Sunshine | F9: 16 | H9: Hotel Sunshine | I9: 1676 | K9: View Hotel | L9: 425 | O9: Mar | P9: 5607723 | Q9: 537684.3 | T9: Birmingham | U9: 1132 | X9: ITA | Y9: 352 | AB9: CID03 | AC9: 564 | AK9: Super Luxury | AL9: 412 | AM9: 2154
A10: Sum of Total Revenue | B10: Sum of Profit | E10: Inn Eve | F10: 6 | H10: Inn Eve | I10: 589 | K10: Opera House | L10: 361 | O10: Apr | P10: 7981312 | Q10: 413129.4 | T10: Chicago | U10: 1504 | X10: UAE | Y10: 421 | AB10: CID08 | AC10: 576 | AK10: Business Class | AL10: 397 | AM10: 2079
A11: 216239836 | B11: 11053892 | E11: Marine Resort | F11: 31 | H11: Marine Resort | I11: 3348 | K11: Hotel Sunshine | L11: 320 | O11: May | P11: 29851647 | Q11: 916020.3 | T11: London | U11: 566 | X11: UK | Y11: 471 | AB11: CID09 | AC11: 531 | AK11: Regular | AL11: 413 | AM11: 1951
E12: Opera House | F12: 20 | H12: Opera House | I12: 2100 | K12: Palace Inn | L12: 256 | O12: Jun | P12: 20920260 | Q12: 1321515.6 | T12: Los Angeles | U12: 752 | X12: USA | Y12: 484 | AB12: CID12 | AC12: 535 | AK12: Single | AL12: 504 | AM12: 1902
A13: Sum of Room Available | B13: Sum of Room Booked | E13: Palace Inn | F13: 10 | H13: Palace Inn | I13: 998 | K13: Empire Grand | L13: 250 | O13: Jul | P13: 4712208 | Q13: 369928.8 | T13: Melbourne | U13: 1270 | AB13: CID14 | AC13: 638 | AF13: {=AF7:AF8} -> Existing | AG13: {=AH7:AH8} -> 0.67857143 | AK13: Luxury | AL13: 338 | AM13: 916
A14: 14688 | B14: 3370 | E14: View Hotel | F14: 18 | H14: View Hotel | I14: 1764 | K14: Inn Eve | L14: 132 | O14: Aug | P14: 21075835 | Q14: 1392664.2 | T14: Milan | U14: 1352 | AB14: CID15 | AC14: 499 | AF14: New | AG14: 0.32142857
O15: Sep | P15: 14042463 | Q15: 809486.1 | T15: Mumbai | U15: 1683 | AB15: CID16 | AC15: 519
O16: Oct | P16: 5119545 | Q16: 819174.3 | T16: New York | U16: 752 | AB16: CID17 | AC16: 613
O17: Nov | P17: 2623788 | Q17: 766944.6 | T17: Rome | U17: 191 | AB17: CID23 | AC17: 670
O18: Dec | P18: 36452732 | Q18: 1645365.6 | T18: Sydney | U18: 2472 | AB18: CID24 | AC18: 470
AB19: CID26 | AC19: 491
K20: {=K7:L14} -> Marine Resort | L20: 1004 | O20: {=O7:O18} -> Jan | P20: {=Q7:Q18} -> 1108296.3 | T20: {=T7:U18} -> Abu Dhabi | U20: 1902 | AB20: CID27 | AC20: 526
K21: Hames Palace | L21: 622 | O21: Feb | P21: 953682 | T21: Bangalore | U21: 1112 | AB21: CID33 | AC21: 527
K22: View Hotel | L22: 425 | O22: Mar | P22: 537684.3 | T22: Birmingham | U22: 1132 | AB22: CID36 | AC22: 564
K23: Opera House | L23: 361 | O23: Apr | P23: 413129.4 | T23: Chicago | U23: 1504 | AB23: CID38 | AC23: 520
K24: Hotel Sunshine | L24: 320 | O24: May | P24: 916020.3 | T24: London | U24: 566 | AB24: CID39 | AC24: 550
K25: Palace Inn | L25: 256 | O25: Jun | P25: 1321515.6 | T25: Los Angeles | U25: 752 | AB25: CID43 | AC25: 532
K26: Empire Grand | L26: 250 | O26: Jul | P26: 369928.8 | T26: Melbourne | U26: 1270 | AB26: CID44 | AC26: 547
K27: Inn Eve | L27: 132 | O27: Aug | P27: 1392664.2 | T27: Milan | U27: 1352 | AB27: CID45 | AC27: 404
O28: Sep | P28: 809486.1 | T28: Mumbai | U28: 1683 | AB28: CID51 | AC28: 515
O29: Oct | P29: 819174.3 | T29: New York | U29: 752 | AB29: CID52 | AC29: 478
O30: Nov | P30: 766944.6 | T30: Rome | U30: 191 | AB30: CID57 | AC30: 443
O31: Dec | P31: 1645365.6 | T31: Sydney | U31: 2472 | AB31: CID58 | AC31: 417
AB32: CID60 | AC32: 550
AB33: CID61 | AC33: 416
AB34: CID63 | AC34: 440

Sheet Dashboard
A6: =Pivot!$H7 -> Empire Grand | C6: =_xlfn.XLOOKUP(A6,Pivot!$H$7:$H$14,Pivot!$I$7:$I$14) -> 2093 | D6: =Pivot!$H8 -> Hames Palace | F6: =_xlfn.XLOOKUP(D6,Pivot!$H$7:$H$14,Pivot!$I$7:$I$14) -> 2120 | G6: =Pivot!$H9 -> Hotel Sunshine | I6: =_xlfn.XLOOKUP(G6,Pivot!$H$7:$H$14,Pivot!$I$7:$I$14) -> 1676 | J6: =Pivot!$H10 -> Inn Eve | L6: =_xlfn.XLOOKUP(J6,Pivot!$H$7:$H$14,Pivot!$I$7:$I$14) -> 589 | M6: =Pivot!$H11 -> Marine Resort | O6: =_xlfn.XLOOKUP(M6,Pivot!$H$7:$H$14,Pivot!$I$7:$I$14) -> 3348 | P6: =Pivot!$H12 -> Opera House | R6: =_xlfn.XLOOKUP(P6,Pivot!$H$7:$H$14,Pivot!$I$7:$I$14) -> 2100 | S6: =Pivot!$H13 -> Palace Inn | U6: =_xlfn.XLOOKUP(S6,Pivot!$H$7:$H$14,Pivot!$I$7:$I$14) -> 998 | V6: =Pivot!$H14 -> View Hotel | X6: =_xlfn.XLOOKUP(V6,Pivot!$H$7:$H$14,Pivot!$I$7:$I$14) -> 1764
